{
  "NAME": "FluX-CR7 Live event ( Auto updated)",
  "AUTHOR": "iVan_Flux",
  "CONTACT (OWNER)": "https://t.me/iVan_flux",
  "TELEGRAM CHANNEL": "https://t.me/api_hub_by_ivan",
  "Last update time": "07:45:42 PM 05-07-2026",
  "Live": "19",
  "Upcoming": "41",
  "events": [
    {
      "match_time": "1783256400",
      "match_status": "live",
      "home_team_name": "Denmark",
      "home_team_logo": "https://cdn.1xapi.com/images/teams/denmark-e93757.png",
      "homeTeamScore": "0",
      "away_team_name": "Ukraine",
      "away_team_logo": "https://cdn.1xapi.com/images/teams/ukraine-4b0f15.png",
      "awayTeamScore": "0",
      "league_name": "WCPEU",
      "league_logo": "https://cdn.1xapi.com/images/teams/nologoo.png",
      "servers": [
        {
          "name": "Server 1",
          "url": "https://pull.niues.live/live/stream-9912106_lsd.m3u8?auth_key=1783264103-0-0-41f06343a38b9dca2e8a6618bd3296bd",
          "type": "direct"
        },
        {
          "name": "Server 2",
          "url": "https://pull.niues.live/live/stream-9912106_lhd.m3u8?auth_key=1783264103-0-0-7b9ac1f56711396ddddefb90e0a192e1",
          "type": "direct"
        }
      ]
    },
    {
      "match_time": 1783256400,
      "match_status": "live",
      "home_team_name": "Grobina FK",
      "home_team_logo": "https://cdn.1xapi.com/images/teams/grobina-fk-853116.png",
      "homeTeamScore": "2",
      "away_team_name": "Tukums 2000",
      "away_team_logo": "https://cdn.1xapi.com/images/teams/tukums-2000-d42a4c.webp",
      "awayTeamScore": "0",
      "league_name": "LAT Higher League",
      "league_logo": "https://cdn.1xapi.com/images/teams/league-lat-higher-league-4c96d6.png",
      "servers": [
        {
          "name": "Server 1",
          "url": "https://hls.lauthaitv.cc/live/grobina-tukums-lathighleague/index.m3u8",
          "type": "direct"
        },
        {
          "name": "Server 2",
          "url": "https://flv.lauthaitv.cc/live/grobina-tukums-lathighleague.flv",
          "type": "direct"
        },
        {
          "name": "Server 3",
          "url": "http://193.47.62.41/hls/ZPPP.m3u8",
          "type": "referer",
          "header": {
            "referer": "http://www.fawanews.sc/",
            "user-agent": "Mozilla/5.0 (Macintosh; Intel Mac OS X 10_15_7) AppleWebKit/537.36 (KHTML, like Gecko) Chrome/149.0.0.0 Safari/537.36"
          }
        }
      ]
    },
    {
      "match_time": 1783256400,
      "match_status": "live",
      "home_team_name": "Grobina",
      "home_team_logo": "https://cdn.1xapi.com/images/teams/grobina-b8584f.webp",
      "homeTeamScore": "0",
      "away_team_name": "Tukums-2000",
      "away_team_logo": "https://cdn.1xapi.com/images/teams/tukums-2000-d42a4c.webp",
      "awayTeamScore": "0",
      "league_name": "Latvian Higher League",
      "league_logo": "https://cdn.1xapi.com/images/teams/nologoo.png",
      "servers": [
        {
          "name": "Server 1",
          "url": "https://pull.niues.live/live/stream-484845_lsd.m3u8?auth_key=1783264103-0-0-98274af43d8a8149c57c8c25743a1923",
          "type": "direct"
        },
        {
          "name": "Server 2",
          "url": "https://pull.niues.live/live/stream-484845_lhd.m3u8?auth_key=1783264103-0-0-dfb1c953f29a1c8c0f7ecd16475ae2f3",
          "type": "direct"
        },
        {
          "name": "Server 3",
          "url": "https://pull.niues.live/live/stream-9912114_lsd.m3u8?auth_key=1783264103-0-0-c80823d01b6608321ba7fd33a590457a",
          "type": "direct"
        },
        {
          "name": "Server 4",
          "url": "https://pull.niues.live/live/stream-9912114_lhd.m3u8?auth_key=1783264103-0-0-b04ade617d33099d2896d730146c6aa2",
          "type": "direct"
        },
        {
          "name": "Server 5",
          "url": "https://pull.niues.live/live/stream-9912015_lsd.m3u8?auth_key=1783264103-0-0-7b29117222b3a656fc0d65f188415ece",
          "type": "direct"
        },
        {
          "name": "Server 6",
          "url": "https://pull.niues.live/live/stream-9912015_lhd.m3u8?auth_key=1783264103-0-0-7fc2573f25fab9f14ffd4443d2513e6f",
          "type": "direct"
        },
        {
          "name": "Server 7",
          "url": "https://pull.niues.live/live/stream-291277_lsd.m3u8?auth_key=1783264103-0-0-0b2ffdbe297e5164a1939e2e51362838",
          "type": "direct"
        },
        {
          "name": "Server 8",
          "url": "https://pull.niues.live/live/stream-291277_lhd.m3u8?auth_key=1783264103-0-0-9d9dd6bbad086edde1dc080b35e768e5",
          "type": "direct"
        },
        {
          "name": "Server 9",
          "url": "https://pull.niues.live/live/stream-582342_lsd.m3u8?auth_key=1783264103-0-0-db6a39d11e521c539333fe1526ad148c",
          "type": "direct"
        },
        {
          "name": "Server 10",
          "url": "https://pull.niues.live/live/stream-582342_lhd.m3u8?auth_key=1783264103-0-0-adc141eb74f1619afeb94e8ee27e609e",
          "type": "direct"
        },
        {
          "name": "Server 11",
          "url": "https://hls.cdnfaster-a.live/live/NGUOITHEP/index.m3u8?expire=2556118740&sign=6d80f4e33c3761371f29a8ca0645fee5",
          "type": "direct"
        },
        {
          "name": "Server 12",
          "url": "https://hls.cdnfaster-a.live/live/MASIEU/index.m3u8?expire=1788427256&sign=b91fcfc36fe72375e8f8cc813de0220b",
          "type": "direct"
        }
      ]
    },
    {
      "match_time": "1783256400",
      "match_status": "live",
      "home_team_name": "Goteborg",
      "home_team_logo": "",
      "homeTeamScore": "0",
      "away_team_name": "AIK",
      "away_team_logo": "",
      "awayTeamScore": "0",
      "league_name": "Sweden Allsvenskan",
      "league_logo": "https://cdn.1xapi.com/images/teams/nologoo.png",
      "servers": [
        {
          "name": "Server 1",
          "url": "http://193.47.62.45/hls/YFFFQQQqqQ.m3u8",
          "type": "referer",
          "header": {
            "referer": "http://www.fawanews.sc/",
            "user-agent": "Mozilla/5.0 (Macintosh; Intel Mac OS X 10_15_7) AppleWebKit/537.36 (KHTML, like Gecko) Chrome/149.0.0.0 Safari/537.36"
          }
        },
        {
          "name": "Server 2",
          "url": "http://193.47.62.58/hls/YFFFQQQqqQ.m3u8",
          "type": "referer",
          "header": {
            "referer": "http://www.fawanews.sc/",
            "user-agent": "Mozilla/5.0 (Macintosh; Intel Mac OS X 10_15_7) AppleWebKit/537.36 (KHTML, like Gecko) Chrome/149.0.0.0 Safari/537.36"
          }
        }
      ]
    },
    {
      "match_time": "1783258200",
      "match_status": "live",
      "home_team_name": "Dinamo Makhachkala B",
      "home_team_logo": "https://static.wex1sora.com/thesports/football/team/64f54442f138adc23d6acf7a85bfe65e.png",
      "homeTeamScore": "0",
      "away_team_name": "Shahter Taganrog",
      "away_team_logo": "https://static.wex1sora.com/thesports/football/team/3ba1629f6265a677c1d9f568152545e5.png",
      "awayTeamScore": "0",
      "league_name": "RUS D3B",
      "league_logo": "https://static.wex1sora.com/thesports/football/competition/6d69860d9e4e8140fce94361b7729b10.png",
      "servers": [
        {
          "name": "Server 1",
          "url": "https://live.bongtv.com/live/sd-6MwdaaRycETQSbv7WL.m3u8?txSecret=698b358e22fa96f394f7aa87d472cfe1&txTime=6A4B0EF5",
          "type": "direct"
        }
      ]
    },
    {
      "match_time": 1783260000,
      "match_status": "live",
      "home_team_name": "FK Atyrau",
      "home_team_logo": "https://cdn.1xapi.com/images/teams/fk-atyrau-b0337c.webp",
      "homeTeamScore": "0",
      "away_team_name": "FK Kaspyi Aktau",
      "away_team_logo": "https://cdn.1xapi.com/images/teams/fk-kaspyi-aktau-dd7dd9.webp",
      "awayTeamScore": "0",
      "league_name": "Kazakhstan Premier League",
      "league_logo": "https://static.wex1sora.com/thesports/football/competition/db5bd04b2bd768144487ef32a4d482e5.png",
      "servers": [
        {
          "name": "Server 1",
          "url": "https://pull.niues.live/live/stream-304148_lsd.m3u8?auth_key=1783264103-0-0-6e76ed008c4122d68d3fe5d1774f6abb",
          "type": "direct"
        },
        {
          "name": "Server 2",
          "url": "https://pull.niues.live/live/stream-304148_lhd.m3u8?auth_key=1783264103-0-0-224e5265333719c3153a1cf621172a35",
          "type": "direct"
        },
        {
          "name": "Server 3",
          "url": "https://pull.niur.live/live/stream-598119_lsd.m3u8?txSecret=8c8e8b9a75b847368de918bbcde629af&txTime=6a4ab9b7",
          "type": "direct"
        },
        {
          "name": "Server 4",
          "url": "https://pull.niur.live/live/stream-598119_lhd.m3u8?txSecret=93b08b420b23bb951acc2f7168292118&txTime=6a4ab9b7",
          "type": "direct"
        },
        {
          "name": "Server 5",
          "url": "https://pull.niues.live/live/stream-406865_lsd.m3u8?auth_key=1783264103-0-0-baa2a4141b60ad0b5699002ca5e3e4ad",
          "type": "direct"
        },
        {
          "name": "Server 6",
          "url": "https://pull.niues.live/live/stream-406865_lhd.m3u8?auth_key=1783264103-0-0-8ed4865c9dab959bcdecd226a12d993e",
          "type": "direct"
        },
        {
          "name": "Server 7",
          "url": "https://pull.niur.live/live/stream-602153_lsd.m3u8?txSecret=dde80e16dd2e813b7b855460f55ac700&txTime=6a4ab9b7",
          "type": "direct"
        },
        {
          "name": "Server 8",
          "url": "https://pull.niur.live/live/stream-602153_lhd.m3u8?txSecret=a0eaa021502d66e92394565b95422d88&txTime=6a4ab9b7",
          "type": "direct"
        },
        {
          "name": "Server 9",
          "url": "https://hls.cdnfaster-a.live/live/KAKA/index.m3u8?expire=1788427256&sign=c34e1c9b22c9ced94eca7e7bf7a81ae6",
          "type": "direct"
        },
        {
          "name": "Server 10",
          "url": "https://hls.cdnfaster-a.live/live/FERNANDO/index.m3u8?expire=1924930980&sign=bab24fb93b0be5c98af9138659989bcb",
          "type": "direct"
        }
      ]
    },
    {
      "match_time": "1783260000",
      "match_status": "live",
      "home_team_name": "Metalist 1925",
      "home_team_logo": "https://static.wex1sora.com/thesports/football/team/67b269a993b1e92fa9b6d786426a60a0.png",
      "homeTeamScore": "0",
      "away_team_name": "Young Boys",
      "away_team_logo": "https://static.wex1sora.com/thesports/football/team/5ee7149b64dc654c7fa2e43c7a0cf12e.png",
      "awayTeamScore": "0",
      "league_name": "International Club Friendly",
      "league_logo": "https://cdn.1xapi.com/images/teams/league-international-club-friendly-84bb81.png",
      "servers": [
        {
          "name": "Server 1",
          "url": "https://live.bongtv.com/live/sd-6MweKx6GxCSXun9X7a.m3u8?txSecret=2ea954876cc1d6b11658a93dd90ba96b&txTime=6A4B0EF5",
          "type": "direct"
        }
      ]
    },
    {
      "match_time": "1783260000",
      "match_status": "live",
      "home_team_name": "Corinthians U20",
      "home_team_logo": "https://static.wex1sora.com/thesports/football/team/3d8fede633a03bdc3e42f80185053c92.png",
      "homeTeamScore": "0",
      "away_team_name": "Sertaozinho U20",
      "away_team_logo": "https://static.wex1sora.com/thesports/football/team/7850da34e9a74544aa5cf18ee6948b57.png",
      "awayTeamScore": "0",
      "league_name": "Giải bóng đá Campeonato Paulista U20 Brazil",
      "league_logo": "https://static.wex1sora.com/thesports/football/competition/8f359c335d62fb21821e514f5b17c65e.png",
      "servers": [
        {
          "name": "Server 1",
          "url": "https://live.bongtv.com/live/sd-6MweaGuXvjXgW5pyz4.m3u8?txSecret=af1e9fd5bd06f904bc00204c03aaba3c&txTime=6A4B0EF5",
          "type": "direct"
        }
      ]
    },
    {
      "match_time": "1783260000",
      "match_status": "live",
      "home_team_name": "FK Lida",
      "home_team_logo": "https://static.wex1sora.com/thesports/football/team/001e7c76f6571d153feb351f0aec9cee.png",
      "homeTeamScore": "0",
      "away_team_name": "Uni X-Labs Minsk",
      "away_team_logo": "https://static.wex1sora.com/thesports/football/team/5c18f9dedc28d16c1d3ca26cd66003e5.png",
      "awayTeamScore": "0",
      "league_name": "Giải hạng Hai Belarus",
      "league_logo": "https://static.wex1sora.com/thesports/football/competition/9e7ae98de79a878ad70d2cb8297aee68.png",
      "servers": [
        {
          "name": "Server 1",
          "url": "https://live.bongtv.com/live/sd-6MwdaoR1KHc6FyZ63W.m3u8?txSecret=0ba9db5143e6616b9125b9f5fb01da1c&txTime=6A4B0EF5",
          "type": "direct"
        }
      ]
    },
    {
      "match_time": "1783260000",
      "match_status": "live",
      "home_team_name": "Cape Verde",
      "home_team_logo": "https://cdn.1xapi.com/images/teams/cape-verde-fd2382.png",
      "homeTeamScore": "0",
      "away_team_name": "Libya",
      "away_team_logo": "https://cdn.1xapi.com/images/teams/libya-13551e.webp",
      "awayTeamScore": "0",
      "league_name": "WCPAF",
      "league_logo": "https://cdn.1xapi.com/images/teams/nologoo.png",
      "servers": [
        {
          "name": "Server 1",
          "url": "https://pull.niues.live/live/stream-9912099_lsd.m3u8?auth_key=1783264103-0-0-7c443a29e8b168c3b397dfd79fb18ef3",
          "type": "direct"
        },
        {
          "name": "Server 2",
          "url": "https://pull.niues.live/live/stream-9912099_lhd.m3u8?auth_key=1783264103-0-0-e12a0fcca7abbb5aa17e9a51b9a69374",
          "type": "direct"
        }
      ]
    },
    {
      "match_time": 1783260000,
      "match_status": "live",
      "home_team_name": "FK Aktobe Lento",
      "home_team_logo": "https://cdn.1xapi.com/images/teams/fk-aktobe-lento-9a1258.webp",
      "homeTeamScore": "0",
      "away_team_name": "FC Zhetysu Taldykorgan",
      "away_team_logo": "https://cdn.1xapi.com/images/teams/fc-zhetysu-taldykorgan-420c0c.webp",
      "awayTeamScore": "0",
      "league_name": "Kazakhstan Premier League",
      "league_logo": "https://static.wex1sora.com/thesports/football/competition/db5bd04b2bd768144487ef32a4d482e5.png",
      "servers": [
        {
          "name": "Server 1",
          "url": "https://pull.niues.live/live/stream-513394_lsd.m3u8?auth_key=1783264103-0-0-487b658f1622962796cd220f9971af59",
          "type": "direct"
        },
        {
          "name": "Server 2",
          "url": "https://pull.niues.live/live/stream-513394_lhd.m3u8?auth_key=1783264103-0-0-3535ab449b6d86cba987d116e55ce424",
          "type": "direct"
        },
        {
          "name": "Server 3",
          "url": "https://live.bongtv.com/live/sd-6Mwd5sHiXPuTxxCG5z.m3u8?txSecret=31b91316149ab0f7736b7f494f402048&txTime=6A4B0EF5",
          "type": "direct"
        },
        {
          "name": "Server 4",
          "url": "http://193.47.62.41/hls/ZPPPQQQQS.m3u8",
          "type": "referer",
          "header": {
            "referer": "http://www.fawanews.sc/",
            "user-agent": "Mozilla/5.0 (Macintosh; Intel Mac OS X 10_15_7) AppleWebKit/537.36 (KHTML, like Gecko) Chrome/149.0.0.0 Safari/537.36"
          }
        },
        {
          "name": "Server 5",
          "url": "https://pull.niur.live/live/stream-610518_lsd.m3u8?txSecret=f0860747f7b169509037203b69ab2441&txTime=6a4ab9b7",
          "type": "direct"
        },
        {
          "name": "Server 6",
          "url": "https://pull.niur.live/live/stream-610518_lhd.m3u8?txSecret=c0a23f6a0d7c508e6d6e53401e28f412&txTime=6a4ab9b7",
          "type": "direct"
        },
        {
          "name": "Server 7",
          "url": "https://pull.niues.live/live/stream-321443_lsd.m3u8?auth_key=1783264103-0-0-2dc4d9189e8fee8bd480cbaf2f89e5c4",
          "type": "direct"
        },
        {
          "name": "Server 8",
          "url": "https://pull.niues.live/live/stream-321443_lhd.m3u8?auth_key=1783264103-0-0-2f79310fde70020c5fdaf6ebce8aa627",
          "type": "direct"
        },
        {
          "name": "Server 9",
          "url": "https://pull.niues.live/live/stream-610677_lsd.m3u8?auth_key=1783264103-0-0-8f44affbd7ae3e8e84089f3941978ec3",
          "type": "direct"
        },
        {
          "name": "Server 10",
          "url": "https://pull.niues.live/live/stream-610677_lhd.m3u8?auth_key=1783264103-0-0-91dcf18617c259d34b701cdf1e0d3ffd",
          "type": "direct"
        },
        {
          "name": "Server 11",
          "url": "https://hls.cdnfaster-a.live/live/LUBO/index.m3u8?expire=1788427256&sign=fa2834495401eb5d1dc40ba2f3bd21c1",
          "type": "direct"
        },
        {
          "name": "Server 12",
          "url": "https://hls.cdnfaster-a.live/live/VOTONG/index.m3u8?expire=1891347600&sign=cbb47d2000b9576a7b34114624ff8299",
          "type": "direct"
        }
      ]
    },
    {
      "match_time": 1783260000,
      "match_status": "live",
      "home_team_name": "07 Vestur Sorvagur",
      "home_team_logo": "https://static.wex1sora.com/thesports/football/team/a23e4dea1f7c8bec2371a1d7bb2ff81d.png",
      "homeTeamScore": "0",
      "away_team_name": "HB Torshavn",
      "away_team_logo": "https://static.wex1sora.com/thesports/football/team/c5e20930f38461d99fa43a7749412368.png",
      "awayTeamScore": "1",
      "league_name": "Faroe Islands Premier League",
      "league_logo": "https://static.wex1sora.com/thesports/football/competition/aab2cb22ab51ad87e4eb116fdcdfcbb3.png",
      "servers": [
        {
          "name": "Server 1",
          "url": "https://live.bongtv.com/live/sd-6MvYqrEqgFsfcTLnNx.m3u8?txSecret=86dc95cbaf17b098dfb953035b4a582e&txTime=6A4B0EF5",
          "type": "direct"
        },
        {
          "name": "Server 2",
          "url": "http://193.47.62.41/hls/ZPPPQQQ.m3u8",
          "type": "referer",
          "header": {
            "referer": "http://www.fawanews.sc/",
            "user-agent": "Mozilla/5.0 (Macintosh; Intel Mac OS X 10_15_7) AppleWebKit/537.36 (KHTML, like Gecko) Chrome/149.0.0.0 Safari/537.36"
          }
        }
      ]
    },
    {
      "match_time": 1783260000,
      "match_status": "live",
      "home_team_name": "Odd Grenland",
      "home_team_logo": "https://cdn.1xapi.com/images/teams/odd-grenland-a80b36.webp",
      "homeTeamScore": "0",
      "away_team_name": "Haugesund",
      "away_team_logo": "https://cdn.1xapi.com/images/teams/haugesund-5d1cdc.png",
      "awayTeamScore": "0",
      "league_name": "Giải hạng nhất quốc gia Na Uy",
      "league_logo": "https://cdn.1xapi.com/images/teams/nologoo.png",
      "servers": [
        {
          "name": "Server 1",
          "url": "https://pull.niues.live/live/stream-531989_lsd.m3u8?auth_key=1783264103-0-0-2a462f444f9440b7aa075b1cc7ac55c2",
          "type": "direct"
        },
        {
          "name": "Server 2",
          "url": "https://pull.niues.live/live/stream-531989_lhd.m3u8?auth_key=1783264103-0-0-54a53d1fc82f0e1022b1dd78c0617476",
          "type": "direct"
        },
        {
          "name": "Server 3",
          "url": "https://live.bongtv.com/live/sd-6MvZ6ETBa6nxXihk7E.m3u8?txSecret=36d835a7867bc4ea8bd39a8d9ed30d5b&txTime=6A4B0EF5",
          "type": "direct"
        },
        {
          "name": "Server 4",
          "url": "http://193.47.62.41/hls/ZPPPQQQQQQ.m3u8",
          "type": "referer",
          "header": {
            "referer": "http://www.fawanews.sc/",
            "user-agent": "Mozilla/5.0 (Macintosh; Intel Mac OS X 10_15_7) AppleWebKit/537.36 (KHTML, like Gecko) Chrome/149.0.0.0 Safari/537.36"
          }
        },
        {
          "name": "Server 5",
          "url": "https://pull.niur.live/live/stream-283501_lsd.m3u8?txSecret=3ad738fd70aa13c12b455c6d0aa75d1b&txTime=6a4ab9b7",
          "type": "direct"
        },
        {
          "name": "Server 6",
          "url": "https://pull.niur.live/live/stream-283501_lhd.m3u8?txSecret=177b1890f3dddb8feee1a4d32521cc28&txTime=6a4ab9b7",
          "type": "direct"
        },
        {
          "name": "Server 7",
          "url": "https://pull.niues.live/live/stream-372746_lsd.m3u8?auth_key=1783264103-0-0-8f5eac010b9d060f54ec5241d5f1a02e",
          "type": "direct"
        },
        {
          "name": "Server 8",
          "url": "https://pull.niues.live/live/stream-372746_lhd.m3u8?auth_key=1783264103-0-0-e8909db11903b5ae7e2798159db929b7",
          "type": "direct"
        },
        {
          "name": "Server 9",
          "url": "https://pull.niur.live/live/stream-534055_lsd.m3u8?txSecret=4619b0d10fe5f5a6741d047c09579cf5&txTime=6a4ab9b7",
          "type": "direct"
        },
        {
          "name": "Server 10",
          "url": "https://pull.niur.live/live/stream-534055_lhd.m3u8?txSecret=f04d2dad4d73e66a7054a693584864c9&txTime=6a4ab9b7",
          "type": "direct"
        }
      ]
    },
    {
      "match_time": 1783260000,
      "match_status": "live",
      "home_team_name": "FK Atyrau",
      "home_team_logo": "https://cdn.1xapi.com/images/teams/fk-atyrau-b0337c.webp",
      "homeTeamScore": "0",
      "away_team_name": "Kaspij Aktau",
      "away_team_logo": "https://static.wex1sora.com/thesports/football/team/093b019417397a95732e569df7f2a8f0.png",
      "awayTeamScore": "0",
      "league_name": "Kazakhstan Premier League",
      "league_logo": "https://static.wex1sora.com/thesports/football/competition/db5bd04b2bd768144487ef32a4d482e5.png",
      "servers": [
        {
          "name": "Server 1",
          "url": "https://live.bongtv.com/live/sd-6Mwd5sHj2oWMMFHR7i.m3u8?txSecret=e79bb07a997942a67a4674d97d727988&txTime=6A4B0EF5",
          "type": "direct"
        },
        {
          "name": "Server 2",
          "url": "http://193.47.62.41/hls/ZPPPQQQQQ.m3u8",
          "type": "referer",
          "header": {
            "referer": "http://www.fawanews.sc/",
            "user-agent": "Mozilla/5.0 (Macintosh; Intel Mac OS X 10_15_7) AppleWebKit/537.36 (KHTML, like Gecko) Chrome/149.0.0.0 Safari/537.36"
          }
        }
      ]
    },
    {
      "match_time": "1783260000",
      "match_status": "live",
      "home_team_name": "Great Britain",
      "home_team_logo": "https://cdn.1xapi.com/images/teams/great-britain-6bf0b4.jpg",
      "homeTeamScore": "0",
      "away_team_name": "Iceland",
      "away_team_logo": "https://cdn.1xapi.com/images/teams/iceland-83166c.webp",
      "awayTeamScore": "0",
      "league_name": "WCPEU",
      "league_logo": "https://cdn.1xapi.com/images/teams/nologoo.png",
      "servers": [
        {
          "name": "Server 1",
          "url": "https://pull.niues.live/live/stream-558264_lsd.m3u8?auth_key=1783264103-0-0-318493af99dd1a057ef46372ee062e32",
          "type": "direct"
        },
        {
          "name": "Server 2",
          "url": "https://pull.niues.live/live/stream-558264_lhd.m3u8?auth_key=1783264103-0-0-2af31d23f7ef54b63877f9950fbb4d3e",
          "type": "direct"
        }
      ]
    },
    {
      "match_time": "1783260000",
      "match_status": "live",
      "home_team_name": "Ypiranga FC",
      "home_team_logo": "https://static.wex1sora.com/thesports/football/team/c8c77c62228caa4d06a9d8819e4a1a4d.png",
      "homeTeamScore": "0",
      "away_team_name": "Paysandu SC",
      "away_team_logo": "https://static.wex1sora.com/thesports/football/team/741486b3cc28391ffd7720dc0a8e2265.png",
      "awayTeamScore": "0",
      "league_name": "Giải hạng ba bóng đá Brasil",
      "league_logo": "https://static.wex1sora.com/thesports/football/competition/79fea55326e48d9b0131971071b189bc.png",
      "servers": [
        {
          "name": "Server 1",
          "url": "https://live.bongtv.com/live/sd-6Mwd5eJgzY13Gdnooz.m3u8?txSecret=0f3b09c0dcdd16a7bf1ca8cecf4a9f55&txTime=6A4B0EF5",
          "type": "direct"
        }
      ]
    },
    {
      "match_time": 1783260000,
      "match_status": "live",
      "home_team_name": "Odds Ballklubb",
      "home_team_logo": "https://cdn.1xapi.com/images/teams/odds-ballklubb-30b875.png",
      "homeTeamScore": "0",
      "away_team_name": "Haugesund",
      "away_team_logo": "https://cdn.1xapi.com/images/teams/haugesund-5d1cdc.png",
      "awayTeamScore": "0",
      "league_name": "Norway Adeccoligaen",
      "league_logo": "https://cdn.1xapi.com/images/teams/nologoo.png",
      "servers": [
        {
          "name": "Server 1",
          "url": "https://hls.cdnfaster-a.live/live/TRIEUTULONG/index.m3u8?expire=1788427256&sign=45e4fdc4bdb8472f513ccc78f57f6070",
          "type": "direct"
        },
        {
          "name": "Server 2",
          "url": "https://hls.cdnfaster-a.live/live/PHIHO/index.m3u8?expire=2556118740&sign=ebc20a588b7a62eb65d12f7372d39a3f",
          "type": "direct"
        }
      ]
    },
    {
      "match_time": "1783260000",
      "match_status": "live",
      "home_team_name": "Tanzania Prisons",
      "home_team_logo": "",
      "homeTeamScore": "0",
      "away_team_name": "Mbeya City",
      "away_team_logo": "",
      "awayTeamScore": "0",
      "league_name": "Tanzania Ligi Kuu Bara",
      "league_logo": "https://cdn.1xapi.com/images/teams/nologoo.png",
      "servers": [
        {
          "name": "Server 1",
          "url": "http://193.47.62.41/hls/ZPPPQ.m3u8",
          "type": "referer",
          "header": {
            "referer": "http://www.fawanews.sc/",
            "user-agent": "Mozilla/5.0 (Macintosh; Intel Mac OS X 10_15_7) AppleWebKit/537.36 (KHTML, like Gecko) Chrome/149.0.0.0 Safari/537.36"
          }
        }
      ]
    },
    {
      "match_time": "1783260000",
      "match_status": "live",
      "home_team_name": "SK Rapid",
      "home_team_logo": "",
      "homeTeamScore": "0",
      "away_team_name": "FK Pardubice",
      "away_team_logo": "",
      "awayTeamScore": "0",
      "league_name": "Friendly Match",
      "league_logo": "https://cdn.1xapi.com/images/teams/nologoo.png",
      "servers": [
        {
          "name": "Server 1",
          "url": "http://193.47.62.42/hls/JBBBQQQQX.m3u8",
          "type": "referer",
          "header": {
            "referer": "http://www.fawanews.sc/",
            "user-agent": "Mozilla/5.0 (Macintosh; Intel Mac OS X 10_15_7) AppleWebKit/537.36 (KHTML, like Gecko) Chrome/149.0.0.0 Safari/537.36"
          }
        }
      ]
    },
    {
      "match_time": 1783261800,
      "match_status": "vs",
      "home_team_name": "Elfsborg",
      "home_team_logo": "https://cdn.1xapi.com/images/teams/elfsborg-c0a5e7.webp",
      "homeTeamScore": "0",
      "away_team_name": "Hammarby",
      "away_team_logo": "https://cdn.1xapi.com/images/teams/hammarby-5e68f1.png",
      "awayTeamScore": "0",
      "league_name": "Giải Vô địch Quốc gia Thụy Điển",
      "league_logo": "https://cdn.1xapi.com/images/teams/nologoo.png",
      "servers": [
        {
          "name": "Server 1",
          "url": "http://193.47.62.45/hls/YFFFQQQqqQQ.m3u8",
          "type": "referer",
          "header": {
            "referer": "http://www.fawanews.sc/",
            "user-agent": "Mozilla/5.0 (Macintosh; Intel Mac OS X 10_15_7) AppleWebKit/537.36 (KHTML, like Gecko) Chrome/149.0.0.0 Safari/537.36"
          }
        },
        {
          "name": "Server 2",
          "url": "http://193.47.62.58/hls/YFFFQQQqqQQ.m3u8",
          "type": "referer",
          "header": {
            "referer": "http://www.fawanews.sc/",
            "user-agent": "Mozilla/5.0 (Macintosh; Intel Mac OS X 10_15_7) AppleWebKit/537.36 (KHTML, like Gecko) Chrome/149.0.0.0 Safari/537.36"
          }
        }
      ]
    },
    {
      "match_time": "1783263600",
      "match_status": "vs",
      "home_team_name": "Saudi Arabia",
      "home_team_logo": "https://cdn.1xapi.com/images/teams/saudi-arabia-5318ef.webp",
      "homeTeamScore": "0",
      "away_team_name": "Qatar",
      "away_team_logo": "https://cdn.1xapi.com/images/teams/qatar-7d8ca4.png",
      "awayTeamScore": "0",
      "league_name": "FIBA WCQL",
      "league_logo": "https://cdn.1xapi.com/images/teams/nologoo.png",
      "servers": []
    },
    {
      "match_time": "1783263600",
      "match_status": "vs",
      "home_team_name": "FT Braunschweig",
      "home_team_logo": "https://static.wex1sora.com/thesports/football/team/fc871d90de849e6e11e2025bfcc94d20.png",
      "homeTeamScore": "0",
      "away_team_name": "Braunschweig",
      "away_team_logo": "https://static.wex1sora.com/thesports/football/team/0a38b45c20a019398526a4944553f8e6.png",
      "awayTeamScore": "0",
      "league_name": "International Club Friendly",
      "league_logo": "https://cdn.1xapi.com/images/teams/league-international-club-friendly-84bb81.png",
      "servers": []
    },
    {
      "match_time": "1783263600",
      "match_status": "vs",
      "home_team_name": "Torpedo Vladimir",
      "home_team_logo": "https://static.wex1sora.com/thesports/football/team/fd07ffcfc100c2a71fdb847835a3bf3e.png",
      "homeTeamScore": "0",
      "away_team_name": "FK Kosmos Dolgoprudny",
      "away_team_logo": "https://static.wex1sora.com/thesports/football/team/e422a1f7ebc0c037a4e699cab19979b5.png",
      "awayTeamScore": "0",
      "league_name": "RUS D3B",
      "league_logo": "https://static.wex1sora.com/thesports/football/competition/6d69860d9e4e8140fce94361b7729b10.png",
      "servers": []
    },
    {
      "match_time": "1783263600",
      "match_status": "vs",
      "home_team_name": "Spartak Moskva II",
      "home_team_logo": "https://static.wex1sora.com/thesports/football/team/dd74b1ccf9444a9ed35690527837393f.png",
      "homeTeamScore": "0",
      "away_team_name": "Murom",
      "away_team_logo": "https://static.wex1sora.com/thesports/football/team/29f52008a69403574920c86860f435d8.png",
      "awayTeamScore": "0",
      "league_name": "RUS D3B",
      "league_logo": "https://static.wex1sora.com/thesports/football/competition/6d69860d9e4e8140fce94361b7729b10.png",
      "servers": []
    },
    {
      "match_time": 1783263600,
      "match_status": "vs",
      "home_team_name": "Kaisar Kyzylorda",
      "home_team_logo": "https://cdn.1xapi.com/images/teams/kaisar-kyzylorda-7eee72.webp",
      "homeTeamScore": "0",
      "away_team_name": "Ertis Pavlodar",
      "away_team_logo": "https://static.wex1sora.com/thesports/football/team/97bfb8ef2c0abc2fd40185debc8dd497.png",
      "awayTeamScore": "0",
      "league_name": "Kazakhstan Premier League",
      "league_logo": "https://static.wex1sora.com/thesports/football/competition/db5bd04b2bd768144487ef32a4d482e5.png",
      "servers": []
    },
    {
      "match_time": "1783263600",
      "match_status": "vs",
      "home_team_name": "Rubin Kazan B",
      "home_team_logo": "https://static.wex1sora.com/thesports/football/team/fa048165d232dc08a183faa073e22f50.png",
      "homeTeamScore": "0",
      "away_team_name": "Krylya Sovetov Samara 2",
      "away_team_logo": "https://static.wex1sora.com/thesports/football/team/341d8290965ecb330ef04de886e3c781.png",
      "awayTeamScore": "0",
      "league_name": "RUS D3B",
      "league_logo": "https://static.wex1sora.com/thesports/football/competition/6d69860d9e4e8140fce94361b7729b10.png",
      "servers": []
    },
    {
      "match_time": "1783263600",
      "match_status": "vs",
      "home_team_name": "Ukraine U19",
      "home_team_logo": "https://cdn.1xapi.com/images/teams/ukraine-u19-12bd1f.png",
      "homeTeamScore": "0",
      "away_team_name": "Ý U19",
      "away_team_logo": "https://static.wex1sora.com/thesports/football/team/775bc655c77d679c193f1982dac04668.png",
      "awayTeamScore": "0",
      "league_name": "Euro U19",
      "league_logo": "https://static.wex1sora.com/thesports/football/competition/a6a98d7ce26efc8afe56aa744eebcefd.png",
      "servers": []
    },
    {
      "match_time": "1783263600",
      "match_status": "vs",
      "home_team_name": "New England Revolution B",
      "home_team_logo": "https://cdn.1xapi.com/images/teams/new-england-revolution-b-ccf18e.webp",
      "homeTeamScore": "0",
      "away_team_name": "Liên minh Philadelphia II",
      "away_team_logo": "https://static.wex1sora.com/thesports/football/team/e9bb64a2a19395e15e8d61c4e04f0b7a.png",
      "awayTeamScore": "0",
      "league_name": "Giải Bóng đá Dự bị Nữ Hoa Kỳ",
      "league_logo": "https://static.wex1sora.com/thesports/football/competition/3d0acf488c114882918b1a8f144e99db.png",
      "servers": []
    },
    {
      "match_time": "1783263600",
      "match_status": "vs",
      "home_team_name": "Widzew Lodz",
      "home_team_logo": "https://static.wex1sora.com/thesports/football/team/2cfa60bf56219aa500c51c8cb28e7777.png",
      "homeTeamScore": "0",
      "away_team_name": "New England Revolution",
      "away_team_logo": "https://static.wex1sora.com/thesports/football/team/f1b7c49790e05778f194ed436515b240.png",
      "awayTeamScore": "0",
      "league_name": "International Club Friendly",
      "league_logo": "https://cdn.1xapi.com/images/teams/league-international-club-friendly-84bb81.png",
      "servers": []
    },
    {
      "match_time": 1783263600,
      "match_status": "vs",
      "home_team_name": "Serbia U19",
      "home_team_logo": "https://cdn.1xapi.com/images/teams/serbia-u19-87dcec.webp",
      "homeTeamScore": "0",
      "away_team_name": "Croatia U19",
      "away_team_logo": "https://cdn.1xapi.com/images/teams/croatia-u19-84b0bf.webp",
      "awayTeamScore": "0",
      "league_name": "UEFA European U19 Championship",
      "league_logo": "https://cdn.1xapi.com/images/teams/nologoo.png",
      "servers": []
    },
    {
      "match_time": "1783263600",
      "match_status": "vs",
      "home_team_name": "New England Revolution B",
      "home_team_logo": "https://cdn.1xapi.com/images/teams/new-england-revolution-b-ccf18e.webp",
      "homeTeamScore": "0",
      "away_team_name": "Philadelphia Union II",
      "away_team_logo": "https://cdn.1xapi.com/images/teams/philadelphia-union-ii-436819.webp",
      "awayTeamScore": "0",
      "league_name": "USA MLSRv",
      "league_logo": "https://cdn.1xapi.com/images/teams/nologoo.png",
      "servers": []
    },
    {
      "match_time": 1783263600,
      "match_status": "vs",
      "home_team_name": "Ordabasy",
      "home_team_logo": "https://cdn.1xapi.com/images/teams/ordabasy-ddd90b.webp",
      "homeTeamScore": "0",
      "away_team_name": "Ulytau Zhezkazgan",
      "away_team_logo": "https://cdn.1xapi.com/images/teams/ulytau-zhezkazgan-d7d5ea.webp",
      "awayTeamScore": "0",
      "league_name": "KAZ Premier League",
      "league_logo": "https://cdn.1xapi.com/images/teams/nologoo.png",
      "servers": []
    },
    {
      "match_time": 1783263600,
      "match_status": "vs",
      "home_team_name": "Kaisar Kyzylorda",
      "home_team_logo": "https://cdn.1xapi.com/images/teams/kaisar-kyzylorda-7eee72.webp",
      "homeTeamScore": "0",
      "away_team_name": "Irtysh Pavlodar",
      "away_team_logo": "https://cdn.1xapi.com/images/teams/irtysh-pavlodar-c6604a.webp",
      "awayTeamScore": "0",
      "league_name": "Kazakhstan Premier League",
      "league_logo": "https://static.wex1sora.com/thesports/football/competition/db5bd04b2bd768144487ef32a4d482e5.png",
      "servers": []
    },
    {
      "match_time": 1783263600,
      "match_status": "vs",
      "home_team_name": "FC Belshina Babruisk",
      "home_team_logo": "https://cdn.1xapi.com/images/teams/fc-belshina-babruisk-349df7.webp",
      "homeTeamScore": "0",
      "away_team_name": "FC Baranovichi",
      "away_team_logo": "https://cdn.1xapi.com/images/teams/fc-baranovichi-114cc3.webp",
      "awayTeamScore": "0",
      "league_name": "Belarusian Premier League",
      "league_logo": "https://cdn.1xapi.com/images/teams/nologoo.png",
      "servers": []
    },
    {
      "match_time": 1783263600,
      "match_status": "vs",
      "home_team_name": "Ukraine U19",
      "home_team_logo": "https://cdn.1xapi.com/images/teams/ukraine-u19-12bd1f.png",
      "homeTeamScore": "0",
      "away_team_name": "Italy U19",
      "away_team_logo": "https://cdn.1xapi.com/images/teams/italy-u19-ef81fe.webp",
      "awayTeamScore": "0",
      "league_name": "UEFA European U19 Championship",
      "league_logo": "https://cdn.1xapi.com/images/teams/nologoo.png",
      "servers": []
    },
    {
      "match_time": "1783263600",
      "match_status": "vs",
      "home_team_name": "Dacia-Buiucani",
      "home_team_logo": "https://cdn.1xapi.com/images/teams/dacia-buiucani-9a662f.png",
      "homeTeamScore": "0",
      "away_team_name": "Real Sireti",
      "away_team_logo": "https://cdn.1xapi.com/images/teams/real-sireti-b7333b.png",
      "awayTeamScore": "0",
      "league_name": "Moldova Divizia Nationala",
      "league_logo": "https://cdn.1xapi.com/images/teams/nologoo.png",
      "servers": []
    },
    {
      "match_time": "1783265400",
      "match_status": "vs",
      "home_team_name": "Mikkelin Palloilijat",
      "home_team_logo": "https://cdn.1xapi.com/images/teams/mikkelin-palloilijat-6dbb34.webp",
      "homeTeamScore": "0",
      "away_team_name": "FC Haka",
      "away_team_logo": "https://cdn.1xapi.com/images/teams/fc-haka-5310bc.webp",
      "awayTeamScore": "0",
      "league_name": "FIN D2",
      "league_logo": "https://cdn.1xapi.com/images/teams/nologoo.png",
      "servers": []
    },
    {
      "match_time": "1783265400",
      "match_status": "vs",
      "home_team_name": "Georgia",
      "home_team_logo": "https://cdn.1xapi.com/images/teams/georgia-c0cdd8.webp",
      "homeTeamScore": "0",
      "away_team_name": "Spain",
      "away_team_logo": "https://cdn.1xapi.com/images/teams/spain-1747d4.png",
      "awayTeamScore": "0",
      "league_name": "WCPEU",
      "league_logo": "https://cdn.1xapi.com/images/teams/nologoo.png",
      "servers": []
    },
    {
      "match_time": "1783265400",
      "match_status": "vs",
      "home_team_name": "MP MIKELI",
      "home_team_logo": "https://cdn.1xapi.com/images/teams/mp-mikeli-2eca0b.png",
      "homeTeamScore": "0",
      "away_team_name": "FC Haka",
      "away_team_logo": "https://cdn.1xapi.com/images/teams/fc-haka-5310bc.webp",
      "awayTeamScore": "0",
      "league_name": "Finland Ykkonen",
      "league_logo": "https://cdn.1xapi.com/images/teams/nologoo.png",
      "servers": []
    },
    {
      "match_time": 1783266300,
      "match_status": "vs",
      "home_team_name": "Siauliai",
      "home_team_logo": "https://cdn.1xapi.com/images/teams/siauliai-089a10.webp",
      "homeTeamScore": "0",
      "away_team_name": "FK Zalgiris Vilnius",
      "away_team_logo": "https://cdn.1xapi.com/images/teams/fk-zalgiris-vilnius-5f321e.webp",
      "awayTeamScore": "0",
      "league_name": "Lithuania - 1.Division",
      "league_logo": "https://cdn.1xapi.com/images/teams/nologoo.png",
      "servers": []
    },
    {
      "match_time": "1783267200",
      "match_status": "vs",
      "home_team_name": "Slovakia",
      "home_team_logo": "https://cdn.1xapi.com/images/teams/slovakia-f64a39.webp",
      "homeTeamScore": "0",
      "away_team_name": "Kosovo",
      "away_team_logo": "https://cdn.1xapi.com/images/teams/kosovo-9eb4c2.webp",
      "awayTeamScore": "0",
      "league_name": "EBCQ",
      "league_logo": "https://cdn.1xapi.com/images/teams/nologoo.png",
      "servers": []
    },
    {
      "match_time": 1783267200,
      "match_status": "vs",
      "home_team_name": "Tartu JK Maag Tammeka",
      "home_team_logo": "https://cdn.1xapi.com/images/teams/tartu-jk-maag-tammeka-6825ac.webp",
      "homeTeamScore": "0",
      "away_team_name": "Harju JK Laagri",
      "away_team_logo": "https://cdn.1xapi.com/images/teams/harju-jk-laagri-d8f0d7.webp",
      "awayTeamScore": "0",
      "league_name": "Estonia Champions League",
      "league_logo": "https://cdn.1xapi.com/images/teams/nologoo.png",
      "servers": []
    },
    {
      "match_time": "1783267200",
      "match_status": "vs",
      "home_team_name": "Belshina",
      "home_team_logo": "",
      "homeTeamScore": "0",
      "away_team_name": "Baranovici",
      "away_team_logo": "",
      "awayTeamScore": "0",
      "league_name": "Belarus Vysshaya Liga",
      "league_logo": "https://cdn.1xapi.com/images/teams/nologoo.png",
      "servers": []
    },
    {
      "match_time": "1783269000",
      "match_status": "vs",
      "home_team_name": "Jordan",
      "home_team_logo": "https://cdn.1xapi.com/images/teams/jordan-d16d37.webp",
      "homeTeamScore": "0",
      "away_team_name": "Iraq",
      "away_team_logo": "https://cdn.1xapi.com/images/teams/iraq-d3b1ce.webp",
      "awayTeamScore": "0",
      "league_name": "FIBA WCQL",
      "league_logo": "https://cdn.1xapi.com/images/teams/nologoo.png",
      "servers": []
    },
    {
      "match_time": 1783269000,
      "match_status": "vs",
      "home_team_name": "Santiago Wanderers",
      "home_team_logo": "https://cdn.1xapi.com/images/teams/santiago-wanderers-6cf200.png",
      "homeTeamScore": "0",
      "away_team_name": "Universidad de Chile",
      "away_team_logo": "https://cdn.1xapi.com/images/teams/universidad-de-chile-9f48d2.png",
      "awayTeamScore": "0",
      "league_name": "Chile Cup",
      "league_logo": "https://cdn.1xapi.com/images/teams/nologoo.png",
      "servers": []
    },
    {
      "match_time": 1783269000,
      "match_status": "vs",
      "home_team_name": "Deportes La Serena",
      "home_team_logo": "https://cdn.1xapi.com/images/teams/deportes-la-serena-13d0d6.png",
      "homeTeamScore": "0",
      "away_team_name": "CSD Antofagasta",
      "away_team_logo": "https://cdn.1xapi.com/images/teams/csd-antofagasta-abc06e.png",
      "awayTeamScore": "0",
      "league_name": "CHI Cup",
      "league_logo": "https://cdn.1xapi.com/images/teams/nologoo.png",
      "servers": []
    },
    {
      "match_time": "1783270800",
      "match_status": "vs",
      "home_team_name": "Olympique de Safi",
      "home_team_logo": "https://cdn.1xapi.com/images/teams/olympique-de-safi-02609a.png",
      "homeTeamScore": "0",
      "away_team_name": "Raja Club Athletic",
      "away_team_logo": "https://cdn.1xapi.com/images/teams/raja-club-athletic-a22653.webp",
      "awayTeamScore": "0",
      "league_name": "MAR D1",
      "league_logo": "https://cdn.1xapi.com/images/teams/nologoo.png",
      "servers": []
    },
    {
      "match_time": 1783270800,
      "match_status": "vs",
      "home_team_name": "Maghreb Fez",
      "home_team_logo": "https://cdn.1xapi.com/images/teams/maghreb-fez-b73c50.png",
      "homeTeamScore": "0",
      "away_team_name": "Olympique Dcheira",
      "away_team_logo": "https://cdn.1xapi.com/images/teams/olympique-dcheira-b960d8.webp",
      "awayTeamScore": "0",
      "league_name": "Botola Pro 1",
      "league_logo": "https://cdn.1xapi.com/images/teams/nologoo.png",
      "servers": []
    },
    {
      "match_time": "1783270800",
      "match_status": "vs",
      "home_team_name": "DHJ Difaa Hassani Jadidi",
      "home_team_logo": "https://cdn.1xapi.com/images/teams/dhj-difaa-hassani-jadidi-594278.webp",
      "homeTeamScore": "0",
      "away_team_name": "Renaissance de Berkane",
      "away_team_logo": "https://cdn.1xapi.com/images/teams/renaissance-de-berkane-b6787e.webp",
      "awayTeamScore": "0",
      "league_name": "MAR D1",
      "league_logo": "https://cdn.1xapi.com/images/teams/nologoo.png",
      "servers": []
    },
    {
      "match_time": 1783270800,
      "match_status": "vs",
      "home_team_name": "Supra Du Quebec",
      "home_team_logo": "https://cdn.1xapi.com/images/teams/supra-du-quebec-65e03b.webp",
      "homeTeamScore": "0",
      "away_team_name": "Forge FC",
      "away_team_logo": "https://cdn.1xapi.com/images/teams/forge-fc-589ce1.webp",
      "awayTeamScore": "0",
      "league_name": "Canadian Premier League",
      "league_logo": "https://cdn.1xapi.com/images/teams/nologoo.png",
      "servers": []
    },
    {
      "match_time": "1783270800",
      "match_status": "vs",
      "home_team_name": "Zimbru Chisinau",
      "home_team_logo": "https://cdn.1xapi.com/images/teams/zimbru-chisinau-4418da.webp",
      "homeTeamScore": "0",
      "away_team_name": "FC Balti",
      "away_team_logo": "https://cdn.1xapi.com/images/teams/fc-balti-e7b7ca.webp",
      "awayTeamScore": "0",
      "league_name": "MOL D1",
      "league_logo": "https://cdn.1xapi.com/images/teams/nologoo.png",
      "servers": []
    },
    {
      "match_time": "1783270800",
      "match_status": "vs",
      "home_team_name": "AS FAR Rabat",
      "home_team_logo": "https://cdn.1xapi.com/images/teams/as-far-rabat-0aab67.webp",
      "homeTeamScore": "0",
      "away_team_name": "Renaissance Zmamra",
      "away_team_logo": "https://cdn.1xapi.com/images/teams/renaissance-zmamra-acfa0d.webp",
      "awayTeamScore": "0",
      "league_name": "MAR D1",
      "league_logo": "https://cdn.1xapi.com/images/teams/nologoo.png",
      "servers": []
    },
    {
      "match_time": 1783270800,
      "match_status": "vs",
      "home_team_name": "Danubio FC",
      "home_team_logo": "https://cdn.1xapi.com/images/teams/danubio-fc-fb1528.webp",
      "homeTeamScore": "0",
      "away_team_name": "CA Juventud",
      "away_team_logo": "https://cdn.1xapi.com/images/teams/ca-juventud-ef6604.webp",
      "awayTeamScore": "0",
      "league_name": "Uruguay Primera Division",
      "league_logo": "https://cdn.1xapi.com/images/teams/nologoo.png",
      "servers": []
    },
    {
      "match_time": "1783270800",
      "match_status": "vs",
      "home_team_name": "FAR Forces Armee Royales",
      "home_team_logo": "https://cdn.1xapi.com/images/teams/far-forces-armee-royales-16ca33.png",
      "homeTeamScore": "0",
      "away_team_name": "Renaissance Zmamra",
      "away_team_logo": "https://cdn.1xapi.com/images/teams/renaissance-zmamra-acfa0d.webp",
      "awayTeamScore": "0",
      "league_name": "Botola Pro 1",
      "league_logo": "https://cdn.1xapi.com/images/teams/nologoo.png",
      "servers": []
    },
    {
      "match_time": 1783274100,
      "match_status": "vs",
      "home_team_name": "FC Torpedo Zhodino",
      "home_team_logo": "https://cdn.1xapi.com/images/teams/fc-torpedo-zhodino-f530d3.png",
      "homeTeamScore": "0",
      "away_team_name": "FK Isloch Minsk",
      "away_team_logo": "https://cdn.1xapi.com/images/teams/fk-isloch-minsk-d8daee.png",
      "awayTeamScore": "0",
      "league_name": "BLR Premier League",
      "league_logo": "https://cdn.1xapi.com/images/teams/nologoo.png",
      "servers": []
    },
    {
      "match_time": "1783274400",
      "match_status": "vs",
      "home_team_name": "Macara",
      "home_team_logo": "https://cdn.1xapi.com/images/teams/macara-7e3a3a.webp",
      "homeTeamScore": "0",
      "away_team_name": "Liga Dep Universitaria Quito",
      "away_team_logo": "https://cdn.1xapi.com/images/teams/liga-dep-universitaria-quito-aab3f0.webp",
      "awayTeamScore": "0",
      "league_name": "ECU D1",
      "league_logo": "https://cdn.1xapi.com/images/teams/nologoo.png",
      "servers": []
    },
    {
      "match_time": "1783274400",
      "match_status": "vs",
      "home_team_name": "Estudiantes de Caseros",
      "home_team_logo": "https://cdn.1xapi.com/images/teams/estudiantes-de-caseros-5bde4e.webp",
      "homeTeamScore": "0",
      "away_team_name": "Racing de Cordoba",
      "away_team_logo": "https://cdn.1xapi.com/images/teams/racing-de-cordoba-c302ca.webp",
      "awayTeamScore": "0",
      "league_name": "ARG D2",
      "league_logo": "https://cdn.1xapi.com/images/teams/nologoo.png",
      "servers": []
    },
    {
      "match_time": 1783274400,
      "match_status": "vs",
      "home_team_name": "Deportivo Madryn",
      "home_team_logo": "https://cdn.1xapi.com/images/teams/deportivo-madryn-d9af78.webp",
      "homeTeamScore": "0",
      "away_team_name": "Colon de Santa Fe",
      "away_team_logo": "https://cdn.1xapi.com/images/teams/colon-de-santa-fe-3a2ea0.webp",
      "awayTeamScore": "0",
      "league_name": "Argentine Division 2",
      "league_logo": "https://cdn.1xapi.com/images/teams/nologoo.png",
      "servers": []
    },
    {
      "match_time": 1783276200,
      "match_status": "vs",
      "home_team_name": "Ferrol Carril Oeste",
      "home_team_logo": "https://cdn.1xapi.com/images/teams/ferrol-carril-oeste-3899a2.webp",
      "homeTeamScore": "0",
      "away_team_name": "San Telmo",
      "away_team_logo": "https://cdn.1xapi.com/images/teams/san-telmo-f2cacc.webp",
      "awayTeamScore": "0",
      "league_name": "Argentine Division 2",
      "league_logo": "https://cdn.1xapi.com/images/teams/nologoo.png",
      "servers": []
    },
    {
      "match_time": "1783276200",
      "match_status": "vs",
      "home_team_name": "Patronato Parana",
      "home_team_logo": "https://cdn.1xapi.com/images/teams/patronato-parana-cc7195.webp",
      "homeTeamScore": "0",
      "away_team_name": "San Martin Tucuman",
      "away_team_logo": "https://cdn.1xapi.com/images/teams/san-martin-tucuman-fefde2.webp",
      "awayTeamScore": "0",
      "league_name": "ARG D2",
      "league_logo": "https://cdn.1xapi.com/images/teams/nologoo.png",
      "servers": []
    }
  ]
}