[
  {
    "match_time": "1781031600",
    "match_status": "live",
    "home_team_name": "England Women",
    "home_team_logo": "https://cdn.1xapi.com/images/teams/england-women-21d3e0.png",
    "homeTeamScore": "0",
    "away_team_name": "Ukraine Women",
    "away_team_logo": "https://cdn.1xapi.com/images/teams/ukraine-women-3b1fc0.png",
    "awayTeamScore": "0",
    "league_name": "WWCPE",
    "league_logo": "https://cdn.1xapi.com/images/teams/nologoo.png",
    "servers": [
      {
        "name": "Server 1",
        "url": "https://pull.niur.live/live/stream-534055_lsd.m3u8?txSecret=ef640fb348b01c0a02334eaf042d391b&txTime=6a28c714",
        "header": {
          "user-agent": "Mozilla/5.0 (Macintosh; Intel Mac OS X 10_15_7) AppleWebKit/605.1.15 (KHTML, like Gecko) Version/18.0 Safari/605.1.15"
        },
        "type": "direct"
      },
      {
        "name": "Server 2",
        "url": "https://pull.niur.live/live/stream-534055_lhd.m3u8?txSecret=e7565c14553a4f61a305a828048ffbd7&txTime=6a28c714",
        "header": {
          "user-agent": "Mozilla/5.0 (Macintosh; Intel Mac OS X 10_15_7) AppleWebKit/605.1.15 (KHTML, like Gecko) Version/18.0 Safari/605.1.15"
        },
        "type": "direct"
      },
      {
        "name": "Server 3",
        "url": "https://pull.niues.live/live/stream-612928_lsd.m3u8?auth_key=1781039300-0-0-bff2cdc691623856ecdf30e308c0795a",
        "header": {
          "user-agent": "Mozilla/5.0 (Macintosh; Intel Mac OS X 10_15_7) AppleWebKit/605.1.15 (KHTML, like Gecko) Version/18.0 Safari/605.1.15"
        },
        "type": "direct"
      },
      {
        "name": "Server 4",
        "url": "https://pull.niues.live/live/stream-612928_lhd.m3u8?auth_key=1781039300-0-0-454b13f6ff7b7457d4ce2b70192d9b5b",
        "header": {
          "user-agent": "Mozilla/5.0 (Macintosh; Intel Mac OS X 10_15_7) AppleWebKit/605.1.15 (KHTML, like Gecko) Version/18.0 Safari/605.1.15"
        },
        "type": "direct"
      },
      {
        "name": "Server 5",
        "url": "https://pull.niues.live/live/stream-589848_lsd.m3u8?auth_key=1781039300-0-0-a5ab4e14e9a78d6a42f301f73d696868",
        "header": {
          "user-agent": "Mozilla/5.0 (Macintosh; Intel Mac OS X 10_15_7) AppleWebKit/605.1.15 (KHTML, like Gecko) Version/18.0 Safari/605.1.15"
        },
        "type": "direct"
      },
      {
        "name": "Server 6",
        "url": "https://pull.niues.live/live/stream-589848_lhd.m3u8?auth_key=1781039300-0-0-5f80f7c468e371e52df604e318bdfaec",
        "header": {
          "user-agent": "Mozilla/5.0 (Macintosh; Intel Mac OS X 10_15_7) AppleWebKit/605.1.15 (KHTML, like Gecko) Version/18.0 Safari/605.1.15"
        },
        "type": "direct"
      },
      {
        "name": "Server 7",
        "url": "https://pull.niues.live/live/stream-602153_lsd.m3u8?auth_key=1781039300-0-0-43b4ff743986c0faf1cf819f4f2d2e20",
        "header": {
          "user-agent": "Mozilla/5.0 (Macintosh; Intel Mac OS X 10_15_7) AppleWebKit/605.1.15 (KHTML, like Gecko) Version/18.0 Safari/605.1.15"
        },
        "type": "direct"
      },
      {
        "name": "Server 8",
        "url": "https://pull.niues.live/live/stream-602153_lhd.m3u8?auth_key=1781039300-0-0-c0b30ce96a5e9f9d6b4a9b9bfe2ac7cb",
        "header": {
          "user-agent": "Mozilla/5.0 (Macintosh; Intel Mac OS X 10_15_7) AppleWebKit/605.1.15 (KHTML, like Gecko) Version/18.0 Safari/605.1.15"
        },
        "type": "direct"
      }
    ]
  },
  {
    "match_time": "1781031600",
    "match_status": "live",
    "home_team_name": "Iceland Women",
    "home_team_logo": "https://cdn.1xapi.com/images/teams/iceland-women-74f541.webp",
    "homeTeamScore": "0",
    "away_team_name": "Spain Women",
    "away_team_logo": "https://cdn.1xapi.com/images/teams/spain-women-ea9b19.png",
    "awayTeamScore": "0",
    "league_name": "WWCPE",
    "league_logo": "https://cdn.1xapi.com/images/teams/nologoo.png",
    "servers": [
      {
        "name": "Server 1",
        "url": "https://pull.niues.live/live/stream-513394_lsd.m3u8?auth_key=1781039300-0-0-90526d9601a1461fdec2a7c7399640d5",
        "header": {
          "user-agent": "Mozilla/5.0 (Macintosh; Intel Mac OS X 10_15_7) AppleWebKit/605.1.15 (KHTML, like Gecko) Version/18.0 Safari/605.1.15"
        },
        "type": "direct"
      },
      {
        "name": "Server 2",
        "url": "https://pull.niues.live/live/stream-513394_lhd.m3u8?auth_key=1781039300-0-0-82a9d6b48c64bcbf1819ae2f5e7da4d0",
        "header": {
          "user-agent": "Mozilla/5.0 (Macintosh; Intel Mac OS X 10_15_7) AppleWebKit/605.1.15 (KHTML, like Gecko) Version/18.0 Safari/605.1.15"
        },
        "type": "direct"
      },
      {
        "name": "Server 3",
        "url": "https://pull.niues.live/live/stream-611382_lsd.m3u8?auth_key=1781039300-0-0-9a5ea4b014c5554cea502324633a3bd9",
        "header": {
          "user-agent": "Mozilla/5.0 (Macintosh; Intel Mac OS X 10_15_7) AppleWebKit/605.1.15 (KHTML, like Gecko) Version/18.0 Safari/605.1.15"
        },
        "type": "direct"
      },
      {
        "name": "Server 4",
        "url": "https://pull.niues.live/live/stream-611382_lhd.m3u8?auth_key=1781039300-0-0-1a6f61add0792492dc0e936cddf0e448",
        "header": {
          "user-agent": "Mozilla/5.0 (Macintosh; Intel Mac OS X 10_15_7) AppleWebKit/605.1.15 (KHTML, like Gecko) Version/18.0 Safari/605.1.15"
        },
        "type": "direct"
      },
      {
        "name": "Server 5",
        "url": "https://pull.niues.live/live/stream-527383_lsd.m3u8?auth_key=1781039300-0-0-7b6fdee5af731e42da252c50fdf701ca",
        "header": {
          "user-agent": "Mozilla/5.0 (Macintosh; Intel Mac OS X 10_15_7) AppleWebKit/605.1.15 (KHTML, like Gecko) Version/18.0 Safari/605.1.15"
        },
        "type": "direct"
      },
      {
        "name": "Server 6",
        "url": "https://pull.niues.live/live/stream-527383_lhd.m3u8?auth_key=1781039300-0-0-281056d616644aaaca9d964e43ed91bb",
        "header": {
          "user-agent": "Mozilla/5.0 (Macintosh; Intel Mac OS X 10_15_7) AppleWebKit/605.1.15 (KHTML, like Gecko) Version/18.0 Safari/605.1.15"
        },
        "type": "direct"
      },
      {
        "name": "Server 7",
        "url": "https://pull.niues.live/live/stream-400722_lsd.m3u8?auth_key=1781039300-0-0-53d844e26c297a388f25a6bc4860444a",
        "header": {
          "user-agent": "Mozilla/5.0 (Macintosh; Intel Mac OS X 10_15_7) AppleWebKit/605.1.15 (KHTML, like Gecko) Version/18.0 Safari/605.1.15"
        },
        "type": "direct"
      },
      {
        "name": "Server 8",
        "url": "https://pull.niues.live/live/stream-400722_lhd.m3u8?auth_key=1781039300-0-0-3f43fe10d26572982f56e08aa25186db",
        "header": {
          "user-agent": "Mozilla/5.0 (Macintosh; Intel Mac OS X 10_15_7) AppleWebKit/605.1.15 (KHTML, like Gecko) Version/18.0 Safari/605.1.15"
        },
        "type": "direct"
      }
    ]
  },
  {
    "match_time": 1781031600,
    "match_status": "live",
    "home_team_name": "Almeria",
    "home_team_logo": "https://cdn.1xapi.com/images/teams/almeria-159837.webp",
    "homeTeamScore": "0",
    "away_team_name": "Castellon",
    "away_team_logo": "https://cdn.1xapi.com/images/teams/castellon-2caf93.webp",
    "awayTeamScore": "0",
    "league_name": "Spanish La Liga 2",
    "league_logo": "https://cdn.1xapi.com/images/teams/nologoo.png",
    "servers": [
      {
        "name": "Server 1",
        "url": "https://pull.niues.live/live/stream-484845_lsd.m3u8?auth_key=1781039300-0-0-676e7daa692e9e9d3651e8a6eab26803",
        "header": {
          "user-agent": "Mozilla/5.0 (Macintosh; Intel Mac OS X 10_15_7) AppleWebKit/605.1.15 (KHTML, like Gecko) Version/18.0 Safari/605.1.15"
        },
        "type": "direct"
      },
      {
        "name": "Server 2",
        "url": "https://pull.niues.live/live/stream-484845_lhd.m3u8?auth_key=1781039300-0-0-d2a8762052dea247d2460209e9c9fb43",
        "header": {
          "user-agent": "Mozilla/5.0 (Macintosh; Intel Mac OS X 10_15_7) AppleWebKit/605.1.15 (KHTML, like Gecko) Version/18.0 Safari/605.1.15"
        },
        "type": "direct"
      },
      {
        "name": "Server 3",
        "url": "https://pull.niues.live/live/stream-387694_lsd.m3u8?auth_key=1781039300-0-0-bfa48d2b35fec6cab4008896911aff7f",
        "header": {
          "user-agent": "Mozilla/5.0 (Macintosh; Intel Mac OS X 10_15_7) AppleWebKit/605.1.15 (KHTML, like Gecko) Version/18.0 Safari/605.1.15"
        },
        "type": "direct"
      },
      {
        "name": "Server 4",
        "url": "https://pull.niues.live/live/stream-387694_lhd.m3u8?auth_key=1781039300-0-0-b7281d874487f02796f7530d8e940195",
        "header": {
          "user-agent": "Mozilla/5.0 (Macintosh; Intel Mac OS X 10_15_7) AppleWebKit/605.1.15 (KHTML, like Gecko) Version/18.0 Safari/605.1.15"
        },
        "type": "direct"
      },
      {
        "name": "Server 5",
        "url": "https://pull.niues.live/live/stream-991140_lsd.m3u8?auth_key=1781039300-0-0-ff353e02fdb813a462252ab0bc613eb8",
        "header": {
          "user-agent": "Mozilla/5.0 (Macintosh; Intel Mac OS X 10_15_7) AppleWebKit/605.1.15 (KHTML, like Gecko) Version/18.0 Safari/605.1.15"
        },
        "type": "direct"
      },
      {
        "name": "Server 6",
        "url": "https://pull.niues.live/live/stream-991140_lhd.m3u8?auth_key=1781039300-0-0-10dd14e1f1754a7e5765105cc3157b94",
        "header": {
          "user-agent": "Mozilla/5.0 (Macintosh; Intel Mac OS X 10_15_7) AppleWebKit/605.1.15 (KHTML, like Gecko) Version/18.0 Safari/605.1.15"
        },
        "type": "direct"
      },
      {
        "name": "Server 7",
        "url": "https://pull.niues.live/live/stream-527384_lsd.m3u8?auth_key=1781039300-0-0-95ab0f68a523766c4bdbe234ff34a41b",
        "header": {
          "user-agent": "Mozilla/5.0 (Macintosh; Intel Mac OS X 10_15_7) AppleWebKit/605.1.15 (KHTML, like Gecko) Version/18.0 Safari/605.1.15"
        },
        "type": "direct"
      },
      {
        "name": "Server 8",
        "url": "https://pull.niues.live/live/stream-527384_lhd.m3u8?auth_key=1781039300-0-0-4d8a1c3c3394345d6a93c6230b2e9f9e",
        "header": {
          "user-agent": "Mozilla/5.0 (Macintosh; Intel Mac OS X 10_15_7) AppleWebKit/605.1.15 (KHTML, like Gecko) Version/18.0 Safari/605.1.15"
        },
        "type": "direct"
      },
      {
        "name": "Server 9",
        "url": "https://hls.cdnfaster-a.live/live/HEINEKEN/index.m3u8?expire=2530639860&sign=03a2e74c3447f79f8c6e80a8fa2ee0b6",
        "type": "direct",
        "header": {
          "Connection": "keep-alive"
        }
      }
    ]
  },
  {
    "match_time": "1781031600",
    "match_status": "live",
    "home_team_name": "France Women",
    "home_team_logo": "https://cdn.1xapi.com/images/teams/france-women-1c902d.png",
    "homeTeamScore": "0",
    "away_team_name": "Ireland Women",
    "away_team_logo": "https://cdn.1xapi.com/images/teams/ireland-women-f710cb.png",
    "awayTeamScore": "0",
    "league_name": "WWCPE",
    "league_logo": "https://cdn.1xapi.com/images/teams/nologoo.png",
    "servers": [
      {
        "name": "Server 1",
        "url": "https://pull.niues.live/live/stream-472241_lsd.m3u8?auth_key=1781039300-0-0-7fab37079a3518881ded4eda04832d26",
        "header": {
          "user-agent": "Mozilla/5.0 (Macintosh; Intel Mac OS X 10_15_7) AppleWebKit/605.1.15 (KHTML, like Gecko) Version/18.0 Safari/605.1.15"
        },
        "type": "direct"
      },
      {
        "name": "Server 2",
        "url": "https://pull.niues.live/live/stream-472241_lhd.m3u8?auth_key=1781039300-0-0-727882bf39330fcc7ac8c7dee135bec7",
        "header": {
          "user-agent": "Mozilla/5.0 (Macintosh; Intel Mac OS X 10_15_7) AppleWebKit/605.1.15 (KHTML, like Gecko) Version/18.0 Safari/605.1.15"
        },
        "type": "direct"
      },
      {
        "name": "Server 3",
        "url": "https://pull.niues.live/live/stream-511367_lsd.m3u8?auth_key=1781039300-0-0-5abdd90f83f36c42100594a0bd65118c",
        "header": {
          "user-agent": "Mozilla/5.0 (Macintosh; Intel Mac OS X 10_15_7) AppleWebKit/605.1.15 (KHTML, like Gecko) Version/18.0 Safari/605.1.15"
        },
        "type": "direct"
      },
      {
        "name": "Server 4",
        "url": "https://pull.niues.live/live/stream-511367_lhd.m3u8?auth_key=1781039300-0-0-e3660a8c236b5762399677ce9e0b1643",
        "header": {
          "user-agent": "Mozilla/5.0 (Macintosh; Intel Mac OS X 10_15_7) AppleWebKit/605.1.15 (KHTML, like Gecko) Version/18.0 Safari/605.1.15"
        },
        "type": "direct"
      },
      {
        "name": "Server 5",
        "url": "https://pull.niur.live/live/stream-598119_lsd.m3u8?txSecret=75685b2e0183d549eb752bfd34070565&txTime=6a28c714",
        "header": {
          "user-agent": "Mozilla/5.0 (Macintosh; Intel Mac OS X 10_15_7) AppleWebKit/605.1.15 (KHTML, like Gecko) Version/18.0 Safari/605.1.15"
        },
        "type": "direct"
      },
      {
        "name": "Server 6",
        "url": "https://pull.niur.live/live/stream-598119_lhd.m3u8?txSecret=a4e3932ae1d042ecbe0071b61d9961f4&txTime=6a28c714",
        "header": {
          "user-agent": "Mozilla/5.0 (Macintosh; Intel Mac OS X 10_15_7) AppleWebKit/605.1.15 (KHTML, like Gecko) Version/18.0 Safari/605.1.15"
        },
        "type": "direct"
      },
      {
        "name": "Server 7",
        "url": "https://pull.niues.live/live/stream-611528_lsd.m3u8?auth_key=1781039300-0-0-d9569eb38797e509506c5e06a4207289",
        "header": {
          "user-agent": "Mozilla/5.0 (Macintosh; Intel Mac OS X 10_15_7) AppleWebKit/605.1.15 (KHTML, like Gecko) Version/18.0 Safari/605.1.15"
        },
        "type": "direct"
      },
      {
        "name": "Server 8",
        "url": "https://pull.niues.live/live/stream-611528_lhd.m3u8?auth_key=1781039300-0-0-ae3625ba84393f5cc9b203d038dea4f6",
        "header": {
          "user-agent": "Mozilla/5.0 (Macintosh; Intel Mac OS X 10_15_7) AppleWebKit/605.1.15 (KHTML, like Gecko) Version/18.0 Safari/605.1.15"
        },
        "type": "direct"
      }
    ]
  },
  {
    "match_time": "1781031600",
    "match_status": "live",
    "home_team_name": "Netherlands Women",
    "home_team_logo": "https://cdn.1xapi.com/images/teams/netherlands-women-bc241d.webp",
    "homeTeamScore": "0",
    "away_team_name": "Poland Women",
    "away_team_logo": "https://cdn.1xapi.com/images/teams/poland-women-45410b.png",
    "awayTeamScore": "0",
    "league_name": "WWCPE",
    "league_logo": "https://cdn.1xapi.com/images/teams/nologoo.png",
    "servers": [
      {
        "name": "Server 1",
        "url": "https://pull.niur.live/live/stream-595715_lsd.m3u8?txSecret=627d773900e1dee719e01528e14fa8af&txTime=6a28c714",
        "header": {
          "user-agent": "Mozilla/5.0 (Macintosh; Intel Mac OS X 10_15_7) AppleWebKit/605.1.15 (KHTML, like Gecko) Version/18.0 Safari/605.1.15"
        },
        "type": "direct"
      },
      {
        "name": "Server 2",
        "url": "https://pull.niur.live/live/stream-595715_lhd.m3u8?txSecret=244a465de33e30a21d9c3c2eb36601a6&txTime=6a28c714",
        "header": {
          "user-agent": "Mozilla/5.0 (Macintosh; Intel Mac OS X 10_15_7) AppleWebKit/605.1.15 (KHTML, like Gecko) Version/18.0 Safari/605.1.15"
        },
        "type": "direct"
      },
      {
        "name": "Server 3",
        "url": "https://pull.niues.live/live/stream-602019_lsd.m3u8?auth_key=1781039300-0-0-ced9d094f718443f34eef2465823f8b0",
        "header": {
          "user-agent": "Mozilla/5.0 (Macintosh; Intel Mac OS X 10_15_7) AppleWebKit/605.1.15 (KHTML, like Gecko) Version/18.0 Safari/605.1.15"
        },
        "type": "direct"
      },
      {
        "name": "Server 4",
        "url": "https://pull.niues.live/live/stream-602019_lhd.m3u8?auth_key=1781039300-0-0-ea7873e1bbaf3105bb5c32f1359e05b1",
        "header": {
          "user-agent": "Mozilla/5.0 (Macintosh; Intel Mac OS X 10_15_7) AppleWebKit/605.1.15 (KHTML, like Gecko) Version/18.0 Safari/605.1.15"
        },
        "type": "direct"
      }
    ]
  },
  {
    "match_time": "1781031600",
    "match_status": "live",
    "home_team_name": "England (W)",
    "home_team_logo": "https://cdn.1xapi.com/images/teams/england-w-ca5eaa.png",
    "homeTeamScore": "2",
    "away_team_name": "Ukraine (W)",
    "away_team_logo": "https://cdn.1xapi.com/images/teams/ukraine-w-c0d456.png",
    "awayTeamScore": "0",
    "league_name": "Women World Cup Europe Qualifying",
    "league_logo": "https://cdn.1xapi.com/images/teams/nologoo.png",
    "servers": [
      {
        "name": "Server 1",
        "url": "https://hls.cdnfaster-a.live/live/TRIEUTULONG/index.m3u8?expire=1788427256&sign=45e4fdc4bdb8472f513ccc78f57f6070",
        "type": "direct",
        "header": {
          "Connection": "keep-alive"
        }
      }
    ]
  },
  {
    "match_time": 1781031600,
    "match_status": "live",
    "home_team_name": "Iceland (W)",
    "home_team_logo": "https://cdn.1xapi.com/images/teams/iceland-w-308894.png",
    "homeTeamScore": "0",
    "away_team_name": "Spain (W)",
    "away_team_logo": "https://cdn.1xapi.com/images/teams/spain-w-62ceb0.png",
    "awayTeamScore": "4",
    "league_name": "Women World Cup Europe Qualifying",
    "league_logo": "https://cdn.1xapi.com/images/teams/nologoo.png",
    "servers": [
      {
        "name": "Server 1",
        "url": "https://hls.cdnfaster-a.live/live/LYQUY/index.m3u8?expire=1891408380&sign=4eb9451ad0178fa8207d583db7d469e3",
        "type": "direct",
        "header": {
          "Connection": "keep-alive"
        }
      },
      {
        "name": "Server 2",
        "url": "https://hls.cdnfaster-a.live/live/VANCONAN/index.m3u8?expire=1830276060&sign=53991e2e589a2f7031dd37b82a585e33",
        "type": "direct",
        "header": {
          "Connection": "keep-alive"
        }
      }
    ]
  },
  {
    "match_time": "1781031600",
    "match_status": "live",
    "home_team_name": "France (W)",
    "home_team_logo": "https://cdn.1xapi.com/images/teams/france-w-64c7d5.png",
    "homeTeamScore": "1",
    "away_team_name": "Ireland (W)",
    "away_team_logo": "https://cdn.1xapi.com/images/teams/ireland-w-5b0296.webp",
    "awayTeamScore": "0",
    "league_name": "Women World Cup Europe Qualifying",
    "league_logo": "https://cdn.1xapi.com/images/teams/nologoo.png",
    "servers": [
      {
        "name": "Server 1",
        "url": "https://hls.cdnfaster-a.live/live/LYUNG1/index.m3u8?expire=1788427256&sign=d5c6932fefdcb98268754f4ccd4aa45d",
        "type": "direct",
        "header": {
          "Connection": "keep-alive"
        }
      }
    ]
  },
  {
    "match_time": "1781031600",
    "match_status": "live",
    "home_team_name": "Netherland (W)",
    "home_team_logo": "https://cdn.1xapi.com/images/teams/netherland-w-b3c0ee.png",
    "homeTeamScore": "1",
    "away_team_name": "Poland (W)",
    "away_team_logo": "https://cdn.1xapi.com/images/teams/poland-w-032247.png",
    "awayTeamScore": "0",
    "league_name": "Women World Cup Europe Qualifying",
    "league_logo": "https://cdn.1xapi.com/images/teams/nologoo.png",
    "servers": [
      {
        "name": "Server 1",
        "url": "https://hls.cdnfaster-a.live/live/NGUOITHEP/index.m3u8?expire=2556118740&sign=6d80f4e33c3761371f29a8ca0645fee5",
        "type": "direct",
        "header": {
          "Connection": "keep-alive"
        }
      }
    ]
  },
  {
    "match_time": 1781035200,
    "match_status": "live",
    "home_team_name": "Maghreb Fez",
    "home_team_logo": "https://cdn.1xapi.com/images/teams/maghreb-fez-b73c50.png",
    "homeTeamScore": "0",
    "away_team_name": "FAR Forces Armee Royales",
    "away_team_logo": "https://cdn.1xapi.com/images/teams/far-forces-armee-royales-16ca33.png",
    "awayTeamScore": "0",
    "league_name": "Botola Pro 1",
    "league_logo": "https://cdn.1xapi.com/images/teams/nologoo.png",
    "servers": [
      {
        "name": "Server 1",
        "url": "https://hls.cdnfaster-a.live/live/LAOHAC/index.m3u8?expire=2556118740&sign=d7e003f1201f61166a559ac474dc7491",
        "type": "direct",
        "header": {
          "Connection": "keep-alive"
        }
      },
      {
        "name": "Server 2",
        "url": "https://hls.cdnfaster-a.live/live/GAUKA/index.m3u8?expire=2530553700&sign=778587d85b2551e2baa61a02917ace14",
        "type": "direct",
        "header": {
          "Connection": "keep-alive"
        }
      }
    ]
  },
  {
    "match_time": 1781042400,
    "match_status": "vs",
    "home_team_name": "Ponte Preta",
    "home_team_logo": "https://cdn.1xapi.com/images/teams/ponte-preta-cb0e8d.png",
    "homeTeamScore": "0",
    "away_team_name": "Cuiaba",
    "away_team_logo": "https://cdn.1xapi.com/images/teams/cuiaba-ce5a0c.webp",
    "awayTeamScore": "0",
    "league_name": "Brazil Serie B",
    "league_logo": "https://cdn.1xapi.com/images/teams/nologoo.png",
    "servers": []
  },
  {
    "match_time": 1781042400,
    "match_status": "vs",
    "home_team_name": "Nautico (PE)",
    "home_team_logo": "https://cdn.1xapi.com/images/teams/nautico-pe-ab09d9.png",
    "homeTeamScore": "0",
    "away_team_name": "Fortaleza",
    "away_team_logo": "https://cdn.1xapi.com/images/teams/fortaleza-bdca02.webp",
    "awayTeamScore": "0",
    "league_name": "Brazil Serie B",
    "league_logo": "https://cdn.1xapi.com/images/teams/nologoo.png",
    "servers": []
  },
  {
    "match_time": "1781046000",
    "match_status": "vs",
    "home_team_name": "Paraguay Women",
    "home_team_logo": "https://cdn.1xapi.com/images/teams/paraguay-women-6afd4f.webp",
    "homeTeamScore": "0",
    "away_team_name": "Colombia Women",
    "away_team_logo": "https://cdn.1xapi.com/images/teams/colombia-women-7fd1ed.png",
    "awayTeamScore": "0",
    "league_name": "CON WLN",
    "league_logo": "https://cdn.1xapi.com/images/teams/nologoo.png",
    "servers": []
  },
  {
    "match_time": "1781046000",
    "match_status": "vs",
    "home_team_name": "Ecuador Women",
    "home_team_logo": "https://cdn.1xapi.com/images/teams/ecuador-women-0d9604.webp",
    "homeTeamScore": "0",
    "away_team_name": "Argentina Women",
    "away_team_logo": "https://cdn.1xapi.com/images/teams/argentina-women-ad8818.webp",
    "awayTeamScore": "0",
    "league_name": "CON WLN",
    "league_logo": "https://cdn.1xapi.com/images/teams/nologoo.png",
    "servers": []
  },
  {
    "match_time": 1781046000,
    "match_status": "vs",
    "home_team_name": "Atletico Ottawa",
    "home_team_logo": "https://cdn.1xapi.com/images/teams/atletico-ottawa-33c5da.webp",
    "homeTeamScore": "0",
    "away_team_name": "Supra Du Quebec",
    "away_team_logo": "https://cdn.1xapi.com/images/teams/supra-du-quebec-65e03b.webp",
    "awayTeamScore": "0",
    "league_name": "Canadian Premier League",
    "league_logo": "https://cdn.1xapi.com/images/teams/nologoo.png",
    "servers": []
  },
  {
    "match_time": 1781046000,
    "match_status": "vs",
    "home_team_name": "Saudi Arabia",
    "home_team_logo": "https://cdn.1xapi.com/images/teams/saudi-arabia-5318ef.png",
    "homeTeamScore": "0",
    "away_team_name": "Senegal",
    "away_team_logo": "https://cdn.1xapi.com/images/teams/senegal-531ba4.png",
    "awayTeamScore": "0",
    "league_name": "International Friendly",
    "league_logo": "https://cdn.1xapi.com/images/teams/nologoo.png",
    "servers": []
  },
  {
    "match_time": "1781046000",
    "match_status": "vs",
    "home_team_name": "Peru Women",
    "home_team_logo": "https://cdn.1xapi.com/images/teams/peru-women-5ac1c5.webp",
    "homeTeamScore": "0",
    "away_team_name": "Bolivia Women",
    "away_team_logo": "https://cdn.1xapi.com/images/teams/bolivia-women-51d64a.webp",
    "awayTeamScore": "0",
    "league_name": "CON WLN",
    "league_logo": "https://cdn.1xapi.com/images/teams/nologoo.png",
    "servers": []
  },
  {
    "match_time": "1781046000",
    "match_status": "vs",
    "home_team_name": "Uruguay Women",
    "home_team_logo": "https://cdn.1xapi.com/images/teams/uruguay-women-8f2dd9.webp",
    "homeTeamScore": "0",
    "away_team_name": "Venezuela Women",
    "away_team_logo": "https://cdn.1xapi.com/images/teams/venezuela-women-1fb36d.webp",
    "awayTeamScore": "0",
    "league_name": "CON WLN",
    "league_logo": "https://cdn.1xapi.com/images/teams/nologoo.png",
    "servers": []
  },
  {
    "match_time": 1781046000,
    "match_status": "vs",
    "home_team_name": "Chicago Sky W",
    "home_team_logo": "https://cdn.1xapi.com/images/teams/chicago-sky-w-530176.webp",
    "homeTeamScore": "0",
    "away_team_name": "Atlanta Dream W",
    "away_team_logo": "https://cdn.1xapi.com/images/teams/atlanta-dream-w-2ff1e4.png",
    "awayTeamScore": "0",
    "league_name": "WNBA",
    "league_logo": "https://cdn.1xapi.com/images/teams/nologoo.png",
    "servers": []
  }
]